AES128_vscode/sbox.v
module sbox(
    input  [7:0] a,
    output reg [7:0] c
);

always @(a)
    case (a)
       8'h00: c=8'h63;
	   8'h01: c=8'h7c;
	   8'h02: c=8'h77;
	   8'h03: c=8'h7b;
	   8'h04: c=8'hf2;
	   8'h05: c=8'h6b;
	   8'h06: c=8'h6f;
	   8'h07: c=8'hc5;
	   8'h08: c=8'h30;
	   8'h09: c=8'h01;
	   8'h0a: c=8'h67;
	   8'h0b: c=8'h2b;
	   8'h0c: c=8'hfe;
	   8'h0d: c=8'hd7;
	   8'h0e: c=8'hab;
	   8'h0f: c=8'h76;
	   8'h10: c=8'hca;
	   8'h11: c=8'h82;
	   8'h12: c=8'hc9;
	   8'h13: c=8'h7d;
	   8'h14: c=8'hfa;
	   8'h15: c=8'h59;
	   8'h16: c=8'h47;
	   8'h17: c=8'hf0;
	   8'h18: c=8'had;
	   8'h19: c=8'hd4;
	   8'h1a: c=8'ha2;
	   8'h1b: c=8'haf;
	   8'h1c: c=8'h9c;
	   8'h1d: c=8'ha4;
	   8'h1e: c=8'h72;
	   8'h1f: c=8'hc0;
	   8'h20: c=8'hb7;
	   8'h21: c=8'hfd;
	   8'h22: c=8'h93;
	   8'h23: c=8'h26;
	   8'h24: c=8'h36;
	   8'h25: c=8'h3f;
	   8'h26: c=8'hf7;
	   8'h27: c=8'hcc;
	   8'h28: c=8'h34;
	   8'h29: c=8'ha5;
	   8'h2a: c=8'he5;
	   8'h2b: c=8'hf1;
	   8'h2c: c=8'h71;
	   8'h2d: c=8'hd8;
	   8'h2e: c=8'h31;
	   8'h2f: c=8'h15;
	   8'h30: c=8'h04;
	   8'h31: c=8'hc7;
	   8'h32: c=8'h23;
	   8'h33: c=8'hc3;
	   8'h34: c=8'h18;
	   8'h35: c=8'h96;
	   8'h36: c=8'h05;
	   8'h37: c=8'h9a;
	   8'h38: c=8'h07;
	   8'h39: c=8'h12;
	   8'h3a: c=8'h80;
	   8'h3b: c=8'he2;
	   8'h3c: c=8'heb;
	   8'h3d: c=8'h27;
	   8'h3e: c=8'hb2;
	   8'h3f: c=8'h75;
	   8'h40: c=8'h09;
	   8'h41: c=8'h83;
	   8'h42: c=8'h2c;
	   8'h43: c=8'h1a;
	   8'h44: c=8'h1b;
	   8'h45: c=8'h6e;
	   8'h46: c=8'h5a;
	   8'h47: c=8'ha0;
	   8'h48: c=8'h52;
	   8'h49: c=8'h3b;
	   8'h4a: c=8'hd6;
	   8'h4b: c=8'hb3;
	   8'h4c: c=8'h29;
	   8'h4d: c=8'he3;
	   8'h4e: c=8'h2f;
	   8'h4f: c=8'h84;
	   8'h50: c=8'h53;
	   8'h51: c=8'hd1;
	   8'h52: c=8'h00;
	   8'h53: c=8'hed;
	   8'h54: c=8'h20;
	   8'h55: c=8'hfc;
	   8'h56: c=8'hb1;
	   8'h57: c=8'h5b;
	   8'h58: c=8'h6a;
	   8'h59: c=8'hcb;
	   8'h5a: c=8'hbe;
	   8'h5b: c=8'h39;
	   8'h5c: c=8'h4a;
	   8'h5d: c=8'h4c;
	   8'h5e: c=8'h58;
	   8'h5f: c=8'hcf;
	   8'h60: c=8'hd0;
	   8'h61: c=8'hef;
	   8'h62: c=8'haa;
	   8'h63: c=8'hfb;
	   8'h64: c=8'h43;
	   8'h65: c=8'h4d;
	   8'h66: c=8'h33;
	   8'h67: c=8'h85;
	   8'h68: c=8'h45;
	   8'h69: c=8'hf9;
	   8'h6a: c=8'h02;
	   8'h6b: c=8'h7f;
	   8'h6c: c=8'h50;
	   8'h6d: c=8'h3c;
	   8'h6e: c=8'h9f;
	   8'h6f: c=8'ha8;
	   8'h70: c=8'h51;
	   8'h71: c=8'ha3;
	   8'h72: c=8'h40;
	   8'h73: c=8'h8f;
	   8'h74: c=8'h92;
	   8'h75: c=8'h9d;
	   8'h76: c=8'h38;
	   8'h77: c=8'hf5;
	   8'h78: c=8'hbc;
	   8'h79: c=8'hb6;
	   8'h7a: c=8'hda;
	   8'h7b: c=8'h21;
	   8'h7c: c=8'h10;
	   8'h7d: c=8'hff;
	   8'h7e: c=8'hf3;
	   8'h7f: c=8'hd2;
	   8'h80: c=8'hcd;
	   8'h81: c=8'h0c;
	   8'h82: c=8'h13;
	   8'h83: c=8'hec;
	   8'h84: c=8'h5f;
	   8'h85: c=8'h97;
	   8'h86: c=8'h44;
	   8'h87: c=8'h17;
	   8'h88: c=8'hc4;
	   8'h89: c=8'ha7;
	   8'h8a: c=8'h7e;
	   8'h8b: c=8'h3d;
	   8'h8c: c=8'h64;
	   8'h8d: c=8'h5d;
	   8'h8e: c=8'h19;
	   8'h8f: c=8'h73;
	   8'h90: c=8'h60;
	   8'h91: c=8'h81;
	   8'h92: c=8'h4f;
	   8'h93: c=8'hdc;
	   8'h94: c=8'h22;
	   8'h95: c=8'h2a;
	   8'h96: c=8'h90;
	   8'h97: c=8'h88;
	   8'h98: c=8'h46;
	   8'h99: c=8'hee;
	   8'h9a: c=8'hb8;
	   8'h9b: c=8'h14;
	   8'h9c: c=8'hde;
	   8'h9d: c=8'h5e;
	   8'h9e: c=8'h0b;
	   8'h9f: c=8'hdb;
	   8'ha0: c=8'he0;
	   8'ha1: c=8'h32;
	   8'ha2: c=8'h3a;
	   8'ha3: c=8'h0a;
	   8'ha4: c=8'h49;
	   8'ha5: c=8'h06;
	   8'ha6: c=8'h24;
	   8'ha7: c=8'h5c;
	   8'ha8: c=8'hc2;
	   8'ha9: c=8'hd3;
	   8'haa: c=8'hac;
	   8'hab: c=8'h62;
	   8'hac: c=8'h91;
	   8'had: c=8'h95;
	   8'hae: c=8'he4;
	   8'haf: c=8'h79;
	   8'hb0: c=8'he7;
	   8'hb1: c=8'hc8;
	   8'hb2: c=8'h37;
	   8'hb3: c=8'h6d;
	   8'hb4: c=8'h8d;
	   8'hb5: c=8'hd5;
	   8'hb6: c=8'h4e;
	   8'hb7: c=8'ha9;
	   8'hb8: c=8'h6c;
	   8'hb9: c=8'h56;
	   8'hba: c=8'hf4;
	   8'hbb: c=8'hea;
	   8'hbc: c=8'h65;
	   8'hbd: c=8'h7a;
	   8'hbe: c=8'hae;
	   8'hbf: c=8'h08;
	   8'hc0: c=8'hba;
	   8'hc1: c=8'h78;
	   8'hc2: c=8'h25;
	   8'hc3: c=8'h2e;
	   8'hc4: c=8'h1c;
	   8'hc5: c=8'ha6;
	   8'hc6: c=8'hb4;
	   8'hc7: c=8'hc6;
	   8'hc8: c=8'he8;
	   8'hc9: c=8'hdd;
	   8'hca: c=8'h74;
	   8'hcb: c=8'h1f;
	   8'hcc: c=8'h4b;
	   8'hcd: c=8'hbd;
	   8'hce: c=8'h8b;
	   8'hcf: c=8'h8a;
	   8'hd0: c=8'h70;
	   8'hd1: c=8'h3e;
	   8'hd2: c=8'hb5;
	   8'hd3: c=8'h66;
	   8'hd4: c=8'h48;
	   8'hd5: c=8'h03;
	   8'hd6: c=8'hf6;
	   8'hd7: c=8'h0e;
	   8'hd8: c=8'h61;
	   8'hd9: c=8'h35;
	   8'hda: c=8'h57;
	   8'hdb: c=8'hb9;
	   8'hdc: c=8'h86;
	   8'hdd: c=8'hc1;
	   8'hde: c=8'h1d;
	   8'hdf: c=8'h9e;
	   8'he0: c=8'he1;
	   8'he1: c=8'hf8;
	   8'he2: c=8'h98;
	   8'he3: c=8'h11;
	   8'he4: c=8'h69;
	   8'he5: c=8'hd9;
	   8'he6: c=8'h8e;
	   8'he7: c=8'h94;
	   8'he8: c=8'h9b;
	   8'he9: c=8'h1e;
	   8'hea: c=8'h87;
	   8'heb: c=8'he9;
	   8'hec: c=8'hce;
	   8'hed: c=8'h55;
	   8'hee: c=8'h28;
	   8'hef: c=8'hdf;
	   8'hf0: c=8'h8c;
	   8'hf1: c=8'ha1;
	   8'hf2: c=8'h89;
	   8'hf3: c=8'h0d;
	   8'hf4: c=8'hbf;
	   8'hf5: c=8'he6;
	   8'hf6: c=8'h42;
	   8'hf7: c=8'h68;
	   8'hf8: c=8'h41;
	   8'hf9: c=8'h99;
	   8'hfa: c=8'h2d;
	   8'hfb: c=8'h0f;
	   8'hfc: c=8'hb0;
	   8'hfd: c=8'h54;
	   8'hfe: c=8'hbb;
	   8'hff: c=8'h16;
	endcase

endmodule

AES128_vscode/Sbox_wrapper.v
`include "sbox.v"

module Sbox_wrapper(
    input         clk,
    input         rst_n,
    input  [127:0] state_in,
    output reg [127:0] state_out
);

    wire [7:0] sbox_out[15:0];

    genvar i;
    generate
        for (i = 0; i < 16; i = i + 1) begin : SBOX_LOOP
            sbox sbox_inst (
                .a(state_in[8*i +: 8]), // đổi lại thứ tự đúng
                .c(sbox_out[i])
            );
        end
    endgenerate

    // Đăng ký output
    always @(posedge clk or negedge rst_n) begin
        if (!rst_n)
            state_out <= 128'd0;
        else
            state_out <= {
                            sbox_out[15], sbox_out[14], sbox_out[13], sbox_out[12],
                            sbox_out[11], sbox_out[10], sbox_out[9],  sbox_out[8],
                            sbox_out[7],  sbox_out[6],  sbox_out[5],  sbox_out[4],
                            sbox_out[3],  sbox_out[2],  sbox_out[1],  sbox_out[0]
};

    end

endmodule

AES128_vscode/KeyLogic_Controller.v
module KeyLogic_Controller (
    input clk, rst_n,
    input Key_rd,
    input [3:0] addr_key,

    output reg done,
    output reg mode,
    output reg [3:0] round,
    output reg [3:0] raddr,
    output reg [3:0] waddr,
    output reg wen,
    output reg src_rf
);

reg [2:0] state, next_state;
localparam IDLE = 0,
           LOAD_KEY = 1,
           ROTWORD_SUBWORD = 2,
           XORR_WRITE_RF = 3,
           DONE = 4;

// State transition
always @(*) begin
    case(state)
        IDLE: begin
            next_state = (Key_rd) ? ROTWORD_SUBWORD : IDLE;
        end
        LOAD_KEY: begin
            next_state = ROTWORD_SUBWORD;
        end
        ROTWORD_SUBWORD: begin
            next_state = XORR_WRITE_RF;
        end
        XORR_WRITE_RF: begin
            next_state = (waddr == 10) ? DONE : ROTWORD_SUBWORD;
        end
        DONE: begin
            next_state = IDLE;
        end
        default: next_state = IDLE;
    endcase
end

// State register
always @(posedge clk or negedge rst_n) begin
    if(~rst_n) begin
        state <= IDLE;
    end
    else begin
        state <= next_state;
    end
end

// Output logic

always @(posedge clk or negedge rst_n) begin
    if (~rst_n) begin
        done <= 0;
        mode <= 0;
        wen <= 0;
        src_rf <= 0;
        round <= 0;
        raddr <= 0;
        waddr <= 0;
    end else begin
        // default values
        done <= 0;
        mode <= 0;
        wen <= 0;
        src_rf <= 0;

        case (state)
            IDLE: begin
                raddr <= addr_key;
                src_rf <= (Key_rd) ? 1 : 0;
                wen <= (Key_rd) ? 1 : 0;
                waddr <= 0;
                round <= 0;
            end

            LOAD_KEY: begin
                waddr <= 0;
                round <= 0;
                raddr <= 0;
//                wen <= 1;
//                src_rf <= 1;
            end

            ROTWORD_SUBWORD: begin
                raddr <= waddr;
            end

            XORR_WRITE_RF: begin
                wen <= 1;
                waddr <= waddr + 1;
                round <= round + 1;
            end

            DONE: begin
                done <= 1;
            end

            default: begin
                // giữ các giá trị
            end
        endcase
    end
end


endmodule

AES128_vscode/Rcon.v
module Rcon (
    input  [3:0] round,        // round index (1 to 10)
    output reg [31:0] rcon_out // output RCON value
);

always @(*) begin
    case (round)
        4'd1:  rcon_out = 32'h01000000;
        4'd2:  rcon_out = 32'h02000000;
        4'd3:  rcon_out = 32'h04000000;
        4'd4:  rcon_out = 32'h08000000;
        4'd5:  rcon_out = 32'h10000000;
        4'd6:  rcon_out = 32'h20000000;
        4'd7:  rcon_out = 32'h40000000;
        4'd8:  rcon_out = 32'h80000000;
        4'd9:  rcon_out = 32'h1B000000;
        4'd10: rcon_out = 32'h36000000;
        default: rcon_out = 32'h00000000; // default (for round = 0 or >10)
    endcase
end

endmodule

AES128_vscode/Xorr.v
`include "Rcon.v"


module Xorr (
    input [127:0] key_prev,
    input [31:0] sub_in,
    input [3:0] round,
    output [127:0] key_new
);

    wire [31:0] rcon;
    wire [31:0] w0, w1, w2, w3;
    wire [31:0] temp, w4, w5, w6, w7;

    // Cắt key_prev thành 4 phần w0..w3
    assign {w0, w1, w2, w3} = key_prev;

    // Tính Rcon từ round
    Rcon u_rcon (
        .round(round),
        .rcon_out(rcon)
    );

    assign temp = sub_in ^ rcon;
    assign w4 = w0 ^ temp;
    assign w5 = w1 ^ w4;
    assign w6 = w2 ^ w5;
    assign w7 = w3 ^ w6;

   assign key_new = {w4, w5, w6, w7};

endmodule

AES128_vscode/RotWord.v
module RotWord (
    input  [31:0] rot_in,   // Input word: 4 bytes (A B C D)
    output [31:0] rot_out   // Output word: rotated (B C D A)
);

assign rot_out = {rot_in[23:0], rot_in[31:24]}; // shift 8 bits to the left

endmodule

AES128_vscode/Registerfile.v
module Registerfile (
    input              clk,
    input              rst_n,

    // Write port
    input              wen,
    input  [3:0]       waddr,   // 4-bit để truy cập 11 thanh ghi
    input  [127:0]     din,

    // Read port
    input  [3:0]       raddr,
    output [127:0] dout
);

    // 11 thanh ghi 128-bit
    reg [127:0] regs [0:10];

    integer i;

    // Write logic
    always @(posedge clk, negedge rst_n) begin
        if (!rst_n) begin
            for (i = 0; i < 11; i = i + 1) begin
                regs[i] <= 128'd0;
            end
        end 
        else begin
            if (wen) begin
                regs[waddr] <= din;
            end
        end
    end

    assign dout = regs[raddr];

endmodule

AES128_vscode/Mux2.v
module Mux2(
    input [127:0] a, b,
    input select,
    output [127:0] c
);

assign c = (select) ? b : a;

endmodule

AES128_vscode/KeyLogic.v
//`include "Mux2.v"
`include "Registerfile.v"
`include "RotWord.v"
`include "Xorr.v"
`include "KeyLogic_Controller.v"

module KeyLogic(
    input clk, rst_n,
    input Key_rd,
    input [3:0] addr_key,
    input [127:0] InputBlk,

    output done,
    output mode, // 0: expansion, 1: 
    output [127:0] Key_data,

    // from - to -sbox
    input [31:0] sub_in,
    output [31:0] rot_out
);

// signal mux2
wire [127:0] key_new;
wire src_rf;

//signal rf
wire wen;
wire [3:0] raddr, waddr;
wire [127:0] din, dout;

Mux2 Mux2_inst(
    .a(key_new),
    .b(InputBlk),
    .select(src_rf),
    .c(din)
);

Registerfile Registerfile_inst(
    .clk(clk),
    .rst_n(rst_n),
    .wen(wen),
    .waddr(waddr),
    .raddr(raddr),
    .din(din),
    .dout(dout)
);
assign Key_data = dout;

RotWord RotWord_inst(
    .rot_in(dout[31:0]),
    .rot_out(rot_out)
);

//signal Xorr
wire [3:0] round;
Xorr Xorr_inst(
    .key_prev(dout),
    .round(round),
    .sub_in(sub_in),
    .key_new(key_new)
);

KeyLogic_Controller KeyLogic_Contronller_inst(
    .clk(clk),
    .rst_n(rst_n),
    .Key_rd(Key_rd),
    .addr_key(addr_key),
    .done(done),
    .mode(mode),
    .round(round),
    .raddr(raddr),
    .waddr(waddr),
    .wen(wen),
    .src_rf(src_rf)
);

endmodule

AES128_vscode/verification_KeyLogic.v
`include "KeyLogic.v"
`include "Sbox_wrapper.v"

module verification_KeyLogic(
    input clk, rst_n,
    input Key_rd,
    input [3:0] addr_key,
    input [127:0] InputBlk,

    output done,
    output mode, // 0: expansion, 1: 
    output [127:0] Key_data
);

wire [31:0] sub_in, rot_out;

KeyLogic KeyLogic_inst(
    .clk(clk),
    .rst_n(rst_n),
    .Key_rd(Key_rd),
    .addr_key(addr_key),
    .InputBlk(InputBlk),
    .done(done),
    .mode(mode),
    .Key_data(Key_data),
    .sub_in(sub_in),
    .rot_out(rot_out)
);
wire [127:0] state_out;
Sbox_wrapper Sbox_wrapper_inst(
    .clk(clk),
    .rst_n(rst_n),
    .state_in({96'd0, rot_out}),
    .state_out(state_out)
);
assign sub_in = state_out[31:0];

endmodule

AES128_vscode/verification_KeyLogic_tb.v
`timescale 1ns/1ps
`include "verification_KeyLogic.v"

module verification_KeyLogic_tb;

    reg clk, rst_n;
    reg Key_rd;
    reg [3:0] addr_key;
    reg [127:0] InputBlk;

    wire done;
    wire mode; // 0: expansion, 1: 
    wire [127:0] Key_data;

    // Instantiate DUT
    verification_KeyLogic dut (
        .clk(clk),
        .rst_n(rst_n),
        .Key_rd(Key_rd),
        .addr_key(addr_key),
        .InputBlk(InputBlk),
        .done(done),
        .Key_data(Key_data)
    );

    // Clock generation
    always #5 clk = ~clk;

    initial begin
        clk = 0;
        rst_n = 0;
        Key_rd = 0;
        addr_key = 0;
        InputBlk = 128'h0;  // AES sample key

        $dumpfile("verification_KeyLogic_tb.vcd");
        $dumpvars(0, verification_KeyLogic_tb);
        // Apply reset
        #10;
        rst_n = 1;
        Key_rd = 1;
        InputBlk = 128'h5468617473206D79204B756E67204675;
        
        #10
        Key_rd = 0;
        // Wait a bit then start key generation
        #20;
        Key_rd = 0;
        InputBlk = 128'h0;

        // Wait for done signal
        wait(done);
        #10 addr_key = 0;
        #10 addr_key = 1;
        #10 addr_key = 2;

        // You can also add `$finish` to end simulation
        #10;
        $finish;
    end

endmodule

AES128_vscode/verification_KeyLogic_tb.vcd
$date
	Mon Apr 28 14:52:42 2025
$end
$version
	Icarus Verilog
$end
$timescale
	1ps
$end
$scope module verification_KeyLogic_tb $end
$var wire 1 ! done $end
$var wire 128 " Key_data [127:0] $end
$var reg 128 # InputBlk [127:0] $end
$var reg 1 $ Key_rd $end
$var reg 4 % addr_key [3:0] $end
$var reg 1 & clk $end
$var reg 1 ' rst_n $end
$scope module dut $end
$var wire 128 ( InputBlk [127:0] $end
$var wire 1 $ Key_rd $end
$var wire 4 ) addr_key [3:0] $end
$var wire 1 & clk $end
$var wire 1 ' rst_n $end
$var wire 32 * sub_in [31:0] $end
$var wire 128 + state_out [127:0] $end
$var wire 32 , rot_out [31:0] $end
$var wire 1 - mode $end
$var wire 1 ! done $end
$var wire 128 . Key_data [127:0] $end
$scope module KeyLogic_inst $end
$var wire 128 / InputBlk [127:0] $end
$var wire 128 0 Key_data [127:0] $end
$var wire 1 $ Key_rd $end
$var wire 4 1 addr_key [3:0] $end
$var wire 1 & clk $end
$var wire 1 ' rst_n $end
$var wire 32 2 sub_in [31:0] $end
$var wire 1 3 wen $end
$var wire 4 4 waddr [3:0] $end
$var wire 1 5 src_rf $end
$var wire 4 6 round [3:0] $end
$var wire 32 7 rot_out [31:0] $end
$var wire 4 8 raddr [3:0] $end
$var wire 1 - mode $end
$var wire 128 9 key_new [127:0] $end
$var wire 128 : dout [127:0] $end
$var wire 1 ! done $end
$var wire 128 ; din [127:0] $end
$scope module KeyLogic_Contronller_inst $end
$var wire 1 $ Key_rd $end
$var wire 4 < addr_key [3:0] $end
$var wire 1 & clk $end
$var wire 1 ' rst_n $end
$var reg 1 ! done $end
$var reg 1 - mode $end
$var reg 3 = next_state [2:0] $end
$var reg 4 > raddr [3:0] $end
$var reg 4 ? round [3:0] $end
$var reg 1 5 src_rf $end
$var reg 3 @ state [2:0] $end
$var reg 4 A waddr [3:0] $end
$var reg 1 3 wen $end
$upscope $end
$scope module Mux2_inst $end
$var wire 128 B b [127:0] $end
$var wire 1 5 select $end
$var wire 128 C c [127:0] $end
$var wire 128 D a [127:0] $end
$upscope $end
$scope module Registerfile_inst $end
$var wire 1 & clk $end
$var wire 128 E din [127:0] $end
$var wire 128 F dout [127:0] $end
$var wire 4 G raddr [3:0] $end
$var wire 1 ' rst_n $end
$var wire 4 H waddr [3:0] $end
$var wire 1 3 wen $end
$var integer 32 I i [31:0] $end
$upscope $end
$scope module RotWord_inst $end
$var wire 32 J rot_in [31:0] $end
$var wire 32 K rot_out [31:0] $end
$upscope $end
$scope module Xorr_inst $end
$var wire 128 L key_prev [127:0] $end
$var wire 4 M round [3:0] $end
$var wire 32 N sub_in [31:0] $end
$var wire 32 O temp [31:0] $end
$var wire 32 P w4 [31:0] $end
$var wire 32 Q w5 [31:0] $end
$var wire 32 R w6 [31:0] $end
$var wire 32 S w7 [31:0] $end
$var wire 32 T w3 [31:0] $end
$var wire 32 U w2 [31:0] $end
$var wire 32 V w1 [31:0] $end
$var wire 32 W w0 [31:0] $end
$var wire 32 X rcon [31:0] $end
$var wire 128 Y key_new [127:0] $end
$scope module u_rcon $end
$var wire 4 Z round [3:0] $end
$var reg 32 [ rcon_out [31:0] $end
$upscope $end
$upscope $end
$upscope $end
$scope module Sbox_wrapper_inst $end
$var wire 1 & clk $end
$var wire 1 ' rst_n $end
$var wire 128 \ state_in [127:0] $end
$var reg 128 ] state_out [127:0] $end
$scope begin SBOX_LOOP[0] $end
$scope module sbox_inst $end
$var wire 8 ^ a [7:0] $end
$var reg 8 _ c [7:0] $end
$upscope $end
$upscope $end
$scope begin SBOX_LOOP[1] $end
$scope module sbox_inst $end
$var wire 8 ` a [7:0] $end
$var reg 8 a c [7:0] $end
$upscope $end
$upscope $end
$scope begin SBOX_LOOP[2] $end
$scope module sbox_inst $end
$var wire 8 b a [7:0] $end
$var reg 8 c c [7:0] $end
$upscope $end
$upscope $end
$scope begin SBOX_LOOP[3] $end
$scope module sbox_inst $end
$var wire 8 d a [7:0] $end
$var reg 8 e c [7:0] $end
$upscope $end
$upscope $end
$scope begin SBOX_LOOP[4] $end
$scope module sbox_inst $end
$var wire 8 f a [7:0] $end
$var reg 8 g c [7:0] $end
$upscope $end
$upscope $end
$scope begin SBOX_LOOP[5] $end
$scope module sbox_inst $end
$var wire 8 h a [7:0] $end
$var reg 8 i c [7:0] $end
$upscope $end
$upscope $end
$scope begin SBOX_LOOP[6] $end
$scope module sbox_inst $end
$var wire 8 j a [7:0] $end
$var reg 8 k c [7:0] $end
$upscope $end
$upscope $end
$scope begin SBOX_LOOP[7] $end
$scope module sbox_inst $end
$var wire 8 l a [7:0] $end
$var reg 8 m c [7:0] $end
$upscope $end
$upscope $end
$scope begin SBOX_LOOP[8] $end
$scope module sbox_inst $end
$var wire 8 n a [7:0] $end
$var reg 8 o c [7:0] $end
$upscope $end
$upscope $end
$scope begin SBOX_LOOP[9] $end
$scope module sbox_inst $end
$var wire 8 p a [7:0] $end
$var reg 8 q c [7:0] $end
$upscope $end
$upscope $end
$scope begin SBOX_LOOP[10] $end
$scope module sbox_inst $end
$var wire 8 r a [7:0] $end
$var reg 8 s c [7:0] $end
$upscope $end
$upscope $end
$scope begin SBOX_LOOP[11] $end
$scope module sbox_inst $end
$var wire 8 t a [7:0] $end
$var reg 8 u c [7:0] $end
$upscope $end
$upscope $end
$scope begin SBOX_LOOP[12] $end
$scope module sbox_inst $end
$var wire 8 v a [7:0] $end
$var reg 8 w c [7:0] $end
$upscope $end
$upscope $end
$scope begin SBOX_LOOP[13] $end
$scope module sbox_inst $end
$var wire 8 x a [7:0] $end
$var reg 8 y c [7:0] $end
$upscope $end
$upscope $end
$scope begin SBOX_LOOP[14] $end
$scope module sbox_inst $end
$var wire 8 z a [7:0] $end
$var reg 8 { c [7:0] $end
$upscope $end
$upscope $end
$scope begin SBOX_LOOP[15] $end
$scope module sbox_inst $end
$var wire 8 | a [7:0] $end
$var reg 8 } c [7:0] $end
$upscope $end
$upscope $end
$upscope $end
$upscope $end
$upscope $end
$enddefinitions $end
#0
$dumpvars
b1100011 }
b0 |
b1100011 {
b0 z
b1100011 y
b0 x
b1100011 w
b0 v
b1100011 u
b0 t
b1100011 s
b0 r
b1100011 q
b0 p
b1100011 o
b0 n
b1100011 m
b0 l
b1100011 k
b0 j
b1100011 i
b0 h
b1100011 g
b0 f
b1100011 e
b0 d
b1100011 c
b0 b
b1100011 a
b0 `
b1100011 _
b0 ^
b0 ]
b0 \
b0 [
b0 Z
b0 Y
b0 X
b0 W
b0 V
b0 U
b0 T
b0 S
b0 R
b0 Q
b0 P
b0 O
b0 N
b0 M
b0 L
b0 K
b0 J
b1011 I
b0 H
b0 G
b0 F
b0 E
b0 D
b0 C
b0 B
b0 A
b0 @
b0 ?
b0 >
b0 =
b0 <
b0 ;
b0 :
b0 9
b0 8
b0 7
b0 6
05
b0 4
03
b0 2
b0 1
b0 0
b0 /
b0 .
0-
b0 ,
b0 +
b0 *
b0 )
b0 (
0'
0&
b0 %
0$
b0 #
b0 "
0!
$end
#5000
b1011 I
1&
#10000
b10 =
0&
b1010100011010000110000101110100011100110010000001101101011110010010000001001011011101010110111001100111001000000100011001110101 #
b1010100011010000110000101110100011100110010000001101101011110010010000001001011011101010110111001100111001000000100011001110101 (
b1010100011010000110000101110100011100110010000001101101011110010010000001001011011101010110111001100111001000000100011001110101 /
b1010100011010000110000101110100011100110010000001101101011110010010000001001011011101010110111001100111001000000100011001110101 B
1$
1'
#15000
b1100011011000110110001101100011 S
b1100011011000110110001101100011 R
b1100011011000110110001101100011 Q
b1100011011000110110001101100011011000110110001101100011011000110110001101100011011000110110001101100011011000110110001101100011 9
b1100011011000110110001101100011011000110110001101100011011000110110001101100011011000110110001101100011011000110110001101100011 D
b1100011011000110110001101100011011000110110001101100011011000110110001101100011011000110110001101100011011000110110001101100011 Y
b1100011011000110110001101100011 P
b1100011011000110110001101100011 O
b11 =
b1010100011010000110000101110100011100110010000001101101011110010010000001001011011101010110111001100111001000000100011001110101 ;
b1010100011010000110000101110100011100110010000001101101011110010010000001001011011101010110111001100111001000000100011001110101 C
b1010100011010000110000101110100011100110010000001101101011110010010000001001011011101010110111001100111001000000100011001110101 E
b1100011011000110110001101100011 *
b1100011011000110110001101100011 2
b1100011011000110110001101100011 N
b10 @
13
15
b1100011011000110110001101100011011000110110001101100011011000110110001101100011011000110110001101100011011000110110001101100011 +
b1100011011000110110001101100011011000110110001101100011011000110110001101100011011000110110001101100011011000110110001101100011 ]
1&
#20000
b0 ;
b0 C
b0 E
0&
b0 #
b0 (
b0 /
b0 B
0$
#25000
b1100011011000110110001101100011011000110110001101100011011000110110001101100011011000110110001101100011011000110110001101100011 ;
b1100011011000110110001101100011011000110110001101100011011000110110001101100011011000110110001101100011011000110110001101100011 C
b1100011011000110110001101100011011000110110001101100011011000110110001101100011011000110110001101100011011000110110001101100011 E
b10 =
05
03
b11 @
1&
#30000
0&
#35000
b1100010011000110110001101100011 S
b1100010011000110110001101100011 R
b1100010011000110110001101100011 Q
b1100010011000110110001101100011011000100110001101100011011000110110001001100011011000110110001101100010011000110110001101100011 ;
b1100010011000110110001101100011011000100110001101100011011000110110001001100011011000110110001101100010011000110110001101100011 C
b1100010011000110110001101100011011000100110001101100011011000110110001001100011011000110110001101100010011000110110001101100011 E
b1100010011000110110001101100011011000100110001101100011011000110110001001100011011000110110001101100010011000110110001101100011 9
b1100010011000110110001101100011011000100110001101100011011000110110001001100011011000110110001101100010011000110110001101100011 D
b1100010011000110110001101100011011000100110001101100011011000110110001001100011011000110110001101100010011000110110001101100011 Y
b1100010011000110110001101100011 P
b1100010011000110110001101100011 O
b1000000000000000000000000 X
b1000000000000000000000000 [
b11 =
b10 @
b1 6
b1 ?
b1 M
b1 Z
b1 4
b1 A
b1 H
13
1&
#40000
0&
#45000
b11111011 a
b11111011 c
b11111011 e
b10101010 _
b11000100110001101100011011000110000000000000000000000000000000001100010011000110110001101100011 ;
b11000100110001101100011011000110000000000000000000000000000000001100010011000110110001101100011 C
b11000100110001101100011011000110000000000000000000000000000000001100010011000110110001101100011 E
b1100011 `
b1100011 b
b1100011 d
b1100010 ^
b0 P
b1100010011000110110001101100011 Q
b0 R
b11000100110001101100011011000110000000000000000000000000000000001100010011000110110001101100011 9
b11000100110001101100011011000110000000000000000000000000000000001100010011000110110001101100011 D
b11000100110001101100011011000110000000000000000000000000000000001100010011000110110001101100011 Y
b1100010011000110110001101100011 S
b1100011011000110110001101100010 \
b1100011011000110110001101100010 ,
b1100011011000110110001101100010 7
b1100011011000110110001101100010 K
b1100010011000110110001101100011 W
b1100010011000110110001101100011 V
b1100010011000110110001101100011 U
b1100010011000110110001101100011 T
b1100010011000110110001101100011 J
b10 =
b1100010011000110110001101100011011000100110001101100011011000110110001001100011011000110110001101100010011000110110001101100011 "
b1100010011000110110001101100011011000100110001101100011011000110110001001100011011000110110001101100010011000110110001101100011 .
b1100010011000110110001101100011011000100110001101100011011000110110001001100011011000110110001101100010011000110110001101100011 0
b1100010011000110110001101100011011000100110001101100011011000110110001001100011011000110110001101100010011000110110001101100011 :
b1100010011000110110001101100011011000100110001101100011011000110110001001100011011000110110001101100010011000110110001101100011 F
b1100010011000110110001101100011011000100110001101100011011000110110001001100011011000110110001101100010011000110110001101100011 L
b1 8
b1 >
b1 G
03
b11 @
1&
#50000
0&
#55000
b11111001111110111111101110101010 S
b10011011100110001001100011001001 R
b11111001111110111111101110101010 Q
b10011011100110001001100011001001111110011111101111111011101010101001101110011000100110001100100111111001111110111111101110101010 ;
b10011011100110001001100011001001111110011111101111111011101010101001101110011000100110001100100111111001111110111111101110101010 C
b10011011100110001001100011001001111110011111101111111011101010101001101110011000100110001100100111111001111110111111101110101010 E
b10011011100110001001100011001001111110011111101111111011101010101001101110011000100110001100100111111001111110111111101110101010 9
b10011011100110001001100011001001111110011111101111111011101010101001101110011000100110001100100111111001111110111111101110101010 D
b10011011100110001001100011001001111110011111101111111011101010101001101110011000100110001100100111111001111110111111101110101010 Y
b10011011100110001001100011001001 P
b11111001111110111111101110101010 O
b10000000000000000000000000 X
b10000000000000000000000000 [
b11 =
b11111011111110111111101110101010 *
b11111011111110111111101110101010 2
b11111011111110111111101110101010 N
b10 @
b10 6
b10 ?
b10 M
b10 Z
b10 4
b10 A
b10 H
13
b1100011011000110110001101100011011000110110001101100011011000110110001101100011011000110110001111111011111110111111101110101010 +
b1100011011000110110001101100011011000110110001101100011011000110110001101100011011000110110001111111011111110111111101110101010 ]
1&
#60000
0&
